tornado_env/__init__.py
tornado_env/config.py
tornado_env/exceptions.py
tornado_env-0.0.2.dist-info/DESCRIPTION.rst
tornado_env-0.0.2.dist-info/METADATA
tornado_env-0.0.2.dist-info/RECORD
tornado_env-0.0.2.dist-info/WHEEL
tornado_env-0.0.2.dist-info/metadata.json
tornado_env-0.0.2.dist-info/top_level.txt
tornado_env-0.0.2.dist-info/zip-safe
